bivouac_framework/__init__.py
bivouac_framework/auth/__init__.py
bivouac_framework/auth/auth_service.py
bivouac_framework/cli/__init__.py
bivouac_framework/cli/commands.py
bivouac_framework/core/__init__.py
bivouac_framework/core/config.py
bivouac_framework/core/module_base.py
bivouac_framework/core/module_registry.py
bivouac_framework/organizations/__init__.py
bivouac_framework/organizations/organization_service.py
bivouac_framework/permissions/__init__.py
bivouac_framework/permissions/permission_service.py
bivouac_framework-0.1.0a0.dist-info/licenses/LICENSE
bivouac_framework-0.1.0a0.dist-info/METADATA
bivouac_framework-0.1.0a0.dist-info/WHEEL
bivouac_framework-0.1.0a0.dist-info/entry_points.txt
bivouac_framework-0.1.0a0.dist-info/top_level.txt
bivouac_framework-0.1.0a0.dist-info/RECORD
