Metadata-Version: 2.4
Name: bivouac-framework
Version: 0.1.0a0
Summary: A modular Flask framework for building scalable web applications
Home-page: https://github.com/bivouac-framework/bivouac-framework
Author: Bivouac Framework Team
Author-email: team@bivouac-framework.com
Classifier: Development Status :: 3 - Alpha
Classifier: Intended Audience :: Developers
Classifier: License :: OSI Approved :: MIT License
Classifier: Operating System :: OS Independent
Classifier: Programming Language :: Python :: 3
Classifier: Programming Language :: Python :: 3.8
Classifier: Programming Language :: Python :: 3.9
Classifier: Programming Language :: Python :: 3.10
Classifier: Programming Language :: Python :: 3.11
Classifier: Topic :: Software Development :: Libraries :: Python Modules
Classifier: Topic :: Internet :: WWW/HTTP :: Dynamic Content
Classifier: Topic :: Internet :: WWW/HTTP :: WSGI :: Application
Requires-Python: >=3.8
License-File: LICENSE
Requires-Dist: Flask>=2.3.0
Requires-Dist: Flask-SQLAlchemy>=3.0.0
Requires-Dist: Flask-User>=1.0.0
Requires-Dist: Flask-WTF>=1.1.0
Requires-Dist: WTForms>=3.0.0
Requires-Dist: SQLAlchemy>=2.0.0
Requires-Dist: Werkzeug>=2.3.0
Requires-Dist: click>=8.0.0
Requires-Dist: python-dotenv>=1.0.0
Provides-Extra: dev
Requires-Dist: pytest>=7.0.0; extra == "dev"
Requires-Dist: pytest-flask>=1.2.0; extra == "dev"
Requires-Dist: black>=23.0.0; extra == "dev"
Requires-Dist: flake8>=6.0.0; extra == "dev"
Requires-Dist: mypy>=1.0.0; extra == "dev"
Dynamic: author
Dynamic: author-email
Dynamic: classifier
Dynamic: description
Dynamic: description-content-type
Dynamic: home-page
Dynamic: license-file
Dynamic: provides-extra
Dynamic: requires-dist
Dynamic: requires-python
Dynamic: summary
